WhatScaler/MinMaxScaler.py
WhatScaler/__init__.py
WhatScaler-0.0.2.dist-info/METADATA
WhatScaler-0.0.2.dist-info/WHEEL
WhatScaler-0.0.2.dist-info/top_level.txt
WhatScaler-0.0.2.dist-info/RECORD
