Metadata-Version: 2.1
Name: WhatScaler
Version: 0.0.2
Summary: MinMaxScaler for AI
Home-page: UNKNOWN
Author: GodZilo (Ido Barel)
Author-email: <vikbarel5@gmail.com>
License: UNKNOWN
Keywords: python,AI,Scaler,MinMaxScaler,numpy
Platform: UNKNOWN
Classifier: Development Status :: 1 - Planning
Classifier: Intended Audience :: Developers
Classifier: Programming Language :: Python :: 3
Classifier: Operating System :: Microsoft :: Windows
